fractal/__init__.py
fractal/core/__init__.py
fractal/core/launcher.py
fractal/core/pipeline.py
fractal/core/base/__init__.py
fractal/core/base/action.py
fractal/core/base/entity.py
fractal/core/base/observations/__init__.py
fractal/core/base/observations/observation.py
fractal/core/base/observations/observations_storage.py
fractal/core/base/observations/sqlite_storage.py
fractal/core/base/strategy/__init__.py
fractal/core/base/strategy/logger.py
fractal/core/base/strategy/result.py
fractal/core/base/strategy/strategy.py
fractal/core/entities/__init__.py
fractal/core/entities/aave.py
fractal/core/entities/default_hedge.py
fractal/core/entities/gmx_v2.py
fractal/core/entities/hedge.py
fractal/core/entities/hyperliquid.py
fractal/core/entities/lending.py
fractal/core/entities/pool.py
fractal/core/entities/single_spot_exchange.py
fractal/core/entities/spot.py
fractal/core/entities/steth.py
fractal/core/entities/uniswap_v2_lp.py
fractal/core/entities/uniswap_v3_lp.py
fractal/core/entities/uniswap_v3_spot.py
fractal/core/entities/models/__init__.py
fractal/core/entities/models/uniswap_v3_fees.py
fractal/loaders/__init__.py
fractal/loaders/aave.py
fractal/loaders/base_loader.py
fractal/loaders/binance.py
fractal/loaders/gmx_v1.py
fractal/loaders/hyperliquid.py
fractal/loaders/structs.py
fractal/loaders/simulations/__init__.py
fractal/loaders/simulations/constant_fundings.py
fractal/loaders/simulations/monte_carlo.py
fractal/loaders/thegraph/__init__.py
fractal/loaders/thegraph/base_graph_loader.py
fractal/loaders/thegraph/lido.py
fractal/loaders/thegraph/uniswap_v2/__init__.py
fractal/loaders/thegraph/uniswap_v2/uniswap_v2_ethereum.py
fractal/loaders/thegraph/uniswap_v2/uniswap_v2_pool.py
fractal/loaders/thegraph/uniswap_v3/__init__.py
fractal/loaders/thegraph/uniswap_v3/uniswap_loader.py
fractal/loaders/thegraph/uniswap_v3/uniswap_v3_arbitrum.py
fractal/loaders/thegraph/uniswap_v3/uniswap_v3_ethereum.py
fractal/loaders/thegraph/uniswap_v3/uniswap_v3_pool.py
fractal_defi-1.2.1.dist-info/LICENSE
fractal_defi-1.2.1.dist-info/METADATA
fractal_defi-1.2.1.dist-info/WHEEL
fractal_defi-1.2.1.dist-info/top_level.txt
fractal_defi-1.2.1.dist-info/RECORD
