Metadata-Version: 2.2
Name: fractal-defi
Version: 1.2.1
Summary: Fractal is the ultimate DeFi research library for strategies development and backtesting created by Logarithm Labs.
Home-page: https://github.com/Logarithm-Labs/Fractal
Author: Logarithm Labs
Author-email: dev@logarithm.fi
Classifier: Programming Language :: Python :: 3
Classifier: License :: OSI Approved :: BSD License
Classifier: Operating System :: OS Independent
Requires-Python: >=3.8, <3.13
License-File: LICENSE
Requires-Dist: mlflow>=2.14.1
Requires-Dist: pandas>=2.2.2
Requires-Dist: numpy>=1.16.0
Requires-Dist: loguru>=0.7.2
Requires-Dist: pytest>=8.2.2
Requires-Dist: pylint>=3.2.5
Requires-Dist: flake8>=7.1.0
Requires-Dist: requests>=2.32.3
Requires-Dist: scipy==1.14.0
Dynamic: author
Dynamic: author-email
Dynamic: classifier
Dynamic: description
Dynamic: description-content-type
Dynamic: home-page
Dynamic: requires-dist
Dynamic: requires-python
Dynamic: summary
